MANIFEST.in
baroque.yml
setup.py
baroque/__init__.py
baroque/baroque.py
baroque/constants.py
baroque.egg-info/PKG-INFO
baroque.egg-info/SOURCES.txt
baroque.egg-info/dependency_links.txt
baroque.egg-info/requires.txt
baroque.egg-info/top_level.txt
baroque/datastructures/__init__.py
baroque/datastructures/bags.py
baroque/datastructures/counters.py
baroque/datastructures/registries.py
baroque/defaults/__init__.py
baroque/defaults/config.py
baroque/defaults/events.py
baroque/defaults/eventtypes.py
baroque/defaults/reactors.py
baroque/entities/__init__.py
baroque/entities/event.py
baroque/entities/eventtype.py
baroque/entities/reactor.py
baroque/entities/topic.py
baroque/exceptions/__init__.py
baroque/exceptions/configuration.py
baroque/exceptions/eventtypes.py
baroque/exceptions/topics.py
baroque/persistence/__init__.py
baroque/persistence/backend.py
baroque/persistence/inmemory.py
baroque/utils/__init__.py
baroque/utils/configreader.py
baroque/utils/importer.py
baroque/utils/timestamp.py
tests/__init__.py
tests/test_baroque.py
tests/test_configuration.py
tests/datastructures/__init__.py
tests/datastructures/test_eventcounter.py
tests/datastructures/test_eventtypesbag.py
tests/datastructures/test_eventtypesregistry.py
tests/datastructures/test_reactorsbag.py
tests/datastructures/test_reactorsregistry.py
tests/datastructures/test_topicsregistry.py
tests/defaults/__init__.py
tests/defaults/test_events.py
tests/defaults/test_eventtypes.py
tests/entities/__init__.py
tests/entities/test_event.py
tests/entities/test_eventtype.py
tests/entities/test_reactor.py
tests/entities/test_topic.py
tests/persistence/__init__.py
tests/persistence/test_dictbackend.py
tests/utils/__init__.py
tests/utils/test_configreader.py
tests/utils/test_importer.py
tests/utils/test_timestamp.py