Metadata-Version: 1.1
Name: baroque
Version: 0.0.2
Summary: Baroque is an event brokering framework with a honey-sweet interface.
Home-page: https://github.com/csparpa/baroque
Author: Claudio Sparpaglione
Author-email: csparpa@gmail.com
License: MIT License
Platform: UNKNOWN
Classifier: License :: OSI Approved :: MIT License
Classifier: Programming Language :: Python :: 3 :: Only
Classifier: Natural Language :: English
Classifier: Operating System :: OS Independent
Classifier: Development Status :: 3 - Alpha
Classifier: Intended Audience :: Developers
Classifier: Topic :: Software Development :: Libraries
Classifier: Topic :: Communications
